src/__init__.py
src/hello.py
firspackage_test-0.0.1.dist-info/METADATA
firspackage_test-0.0.1.dist-info/WHEEL
firspackage_test-0.0.1.dist-info/top_level.txt
firspackage_test-0.0.1.dist-info/RECORD
